fossbot_lib/common/data_structures/__init__.py
fossbot_lib/common/data_structures/configuration.py
fossbot_lib/common/interfaces/__init__.py
fossbot_lib/common/interfaces/control_interfaces.py
fossbot_lib/common/interfaces/robot_interface.py
fossbot_lib/common/interfaces/sim_gym_interface.py
fossbot_lib/parameters_parser/__init__.py
fossbot_lib/parameters_parser/parser.py
fossbot_lib/real_robot/__init__.py
fossbot_lib/real_robot/control.py
fossbot_lib/real_robot/fossbot.py
fossbot_lib_real-0.1.3.5.dist-info/METADATA
fossbot_lib_real-0.1.3.5.dist-info/WHEEL
fossbot_lib_real-0.1.3.5.dist-info/top_level.txt
fossbot_lib_real-0.1.3.5.dist-info/RECORD
